setup.py
asyncio_yify.egg-info/PKG-INFO
asyncio_yify.egg-info/SOURCES.txt
asyncio_yify.egg-info/dependency_links.txt
asyncio_yify.egg-info/requires.txt
asyncio_yify.egg-info/top_level.txt
yify/__init__.py
yify/api.py