Metadata-Version: 1.0
Name: asyncio-yify
Version: 0.0.7
Summary: Damned fast YIFY parser using Asyncio
Home-page: https://github.com/davidyen1124/Asyncio-YIFY
Author: davidyen1124
Author-email: davidyen1124@gmail.com
License: UNKNOWN
Keywords: yify parser movies asyncio
Platform: UNKNOWN
